benpkg/__init__.py
benpkg-0.7.0.dist-info/WHEEL
benpkg-0.7.0.dist-info/METADATA
benpkg-0.7.0.dist-info/RECORD
