Metadata-Version: 2.1
Name: benpkg
Version: 0.7.0
Summary: 
Author: Ben-Cheng
Author-email: bcheng@linz.govt.nz
Requires-Python: >=3.6,<4.0
Classifier: Programming Language :: Python :: 3
Classifier: Programming Language :: Python :: 3.6
Classifier: Programming Language :: Python :: 3.7
Classifier: Programming Language :: Python :: 3.8
Requires-Dist: pyqt5 (==5.11.2)
